{
  "$schema": "http://json-schema.org/draft-07/schema#",
  "type": "object",
  "properties": {
    "pipelineUp": {
      "type": "boolean"
    },
    "loggingOk": {
      "type": "boolean"
    },
    "loggingSinkUp": {
      "type": "boolean"
    },
    "tracingOk": {
      "type": "boolean"
    },
    "tracingUp": {
      "type": "boolean"
    },
    "metricsHttpOk": {
      "type": "boolean"
    },
    "runId": {
      "type": "object"
    },
    "correlationId": {
      "type": "object"
    },
    "diagnostics": {
      "type": "object"
    }
  },
  "required": [
    "pipelineUp",
    "loggingOk",
    "loggingSinkUp",
    "tracingOk",
    "tracingUp",
    "metricsHttpOk",
    "runId",
    "correlationId",
    "diagnostics"
  ],
  "additionalProperties": false
}
